setup.cfg
setup.py
pysochain/__init__.py
python_sochain_api.egg-info/PKG-INFO
python_sochain_api.egg-info/SOURCES.txt
python_sochain_api.egg-info/dependency_links.txt
python_sochain_api.egg-info/requires.txt
python_sochain_api.egg-info/top_level.txt
python_sochain_api.egg-info/zip-safe