Metadata-Version: 1.1
Name: python-sochain-api
Version: 0.0.2
Summary: Python API for interacting with chain.so.
Home-page: https://github.com/Klathmon/python-sochain-api
Author: Gregory Benner
Author-email: gregbenner1@gmail.com
License: MIT
Download-URL: https://github.com/Klathmon/python-sochain-api/archive/0.0.1.tar.gz
Platform: UNKNOWN
